carestack/__init__.py
carestack/default_config.py
carestack/ai/__init__.py
carestack/ai/ai_dto.py
carestack/ai/ai_service.py
carestack/ai/ai_service_test.py
carestack/ai/ai_utils.py
carestack/appointment/__init__.py
carestack/appointment/appointment_dto.py
carestack/appointment/appointment_service.py
carestack/appointment/appointment_test.py
carestack/base/__init__.py
carestack/base/base_service.py
carestack/base/base_types.py
carestack/base/errors.py
carestack/common/__init__.py
carestack/common/config_test.py
carestack/common/enums.py
carestack/common/error_validation.py
carestack/encounter/__init__.py
carestack/encounter/encounter_service.py
carestack/encounter/encounter_test.py
carestack/encounter/document_linking/__init__.py
carestack/encounter/document_linking/document_linking.py
carestack/encounter/document_linking/schema.py
carestack/encounter/document_linking/dto/__init__.py
carestack/encounter/document_linking/dto/create_care_context_dto.py
carestack/encounter/document_linking/dto/health_document_linking_dto.py
carestack/encounter/document_linking/dto/health_information_dto.py
carestack/encounter/document_linking/dto/link_care_context_dto.py
carestack/encounter/document_linking/dto/update_visit_records_dto.py
carestack/encounter/dto/__init__.py
carestack/encounter/dto/encounter_dto.py
carestack/lookup/__init__.py
carestack/lookup/lookup_dto.py
carestack/lookup/lookup_service.py
carestack/organization/__init__.py
carestack/organization/organization_dto.py
carestack/organization/organization_service.py
carestack/organization/organization_service_test.py
carestack/organization/hfr/__init__.py
carestack/patient/__init__.py
carestack/patient/patient_dto.py
carestack/patient/patient_service.py
carestack/patient/patient_service_test.py
carestack/patient/abha/__init__.py
carestack/patient/abha/abha_dto.py
carestack/patient/abha/abha_service.py
carestack/patient/abha/abha_service_test.py
carestack/patient/abha/create_abha.py
carestack/patient/abha/encrypt_data.py
carestack-0.1.22.10.dist-info/METADATA
carestack-0.1.22.10.dist-info/WHEEL
carestack-0.1.22.10.dist-info/top_level.txt
carestack-0.1.22.10.dist-info/RECORD
