Metadata-Version: 2.4
Name: carestack
Version: 0.1.22.10
Summary: SDK for EHR Services
Author-email: achalahealth <venkatesh.dakarapu@achalasolutions.com>
Project-URL: Homepage, https://github.com/achalahealth/ehrsdk
Classifier: Programming Language :: Python :: 3
Classifier: Programming Language :: Python :: 3.8
Classifier: Programming Language :: Python :: 3.9
Classifier: Programming Language :: Python :: 3.10
Classifier: Programming Language :: Python :: 3.11
Classifier: Programming Language :: Python :: 3.12
Classifier: Programming Language :: Python :: 3.13
Classifier: Operating System :: OS Independent
Requires-Python: >=3.8
Requires-Dist: httpx>=0.25.0
Requires-Dist: pydantic>=2.0.0
Requires-Dist: pydantic[email]>=2.0.0
Requires-Dist: typing_extensions
Requires-Dist: python-dotenv>=1.0.1
Requires-Dist: cryptography>=3.0
Requires-Dist: python-jose[cryptography]>=3.3.0
Provides-Extra: dev
Requires-Dist: pytest; extra == "dev"
Requires-Dist: pytest-asyncio; extra == "dev"
Requires-Dist: setuptools>=64; extra == "dev"
Requires-Dist: wheel; extra == "dev"
